<?xml version="1.0" encoding="UTF-8"?>
<beans xmlns="http://www.springframework.org/schema/beans" 
		xmlns:xsi="http://www.w3.org/2001/XMLSchema-instance"
        xmlns:p="http://www.springframework.org/schema/p"
        xmlns:context="http://www.springframework.org/schema/context"
        xmlns:mvc="http://www.springframework.org/schema/mvc"
        xmlns:websocket="http://www.springframework.org/schema/websocket"
        xsi:schemaLocation="http://www.springframework.org/schema/beans http://www.springframework.org/schema/beans/spring-beans-3.2.xsd
                http://www.springframework.org/schema/context http://www.springframework.org/schema/context/spring-context-3.2.xsd
                http://www.springframework.org/schema/mvc http://www.springframework.org/schema/mvc/spring-mvc-3.2.xsd
                http://www.springframework.org/schema/websocket http://www.springframework.org/schema/websocket/spring-websocket-4.1.xsd">

    <!-- 패키지 내 Controller, Service, Repository 클래스의 auto detect를 위한 mvc 설정 -->
    <context:component-scan base-package="egovframework" use-default-filters="false">
        <context:include-filter type="annotation" expression="org.springframework.stereotype.Controller"/>
    </context:component-scan>

    <!-- 서블릿컨네이너상의 exception에 대한 오류 페이지를 연결하는 mvc 설정-->
    <!-- <bean class="org.springframework.web.servlet.handler.SimpleMappingExceptionResolver">-->
	<bean class="egovframework.com.cmm.web.LoggingExceptionResolver">
        <property name="defaultErrorView" value="cmm/error/egovError"/>
        <property name="defaultStatusCode" value="500"/>
        <property name="exceptionMappings">
            <props>
                <prop key="org.springframework.dao.DataAccessException">cmm/error/dataAccessFailure</prop>
                <prop key="org.springframework.transaction.TransactionException">cmm/error/transactionFailure</prop>
                <prop key="org.egovframe.rte.fdl.cmmn.exception.EgovBizException">cmm/error/egovError</prop>
                <prop key="org.springframework.security.AccessDeniedException">cmm/error/accessDenied</prop>
            </props>
        </property>
    </bean>
    
	<!--     뷰리절버로 jsp 찾기전에 JSON 찾는다 -->
    <bean class="org.springframework.web.servlet.view.BeanNameViewResolver" p:order="0"/>

    <!-- 화면처리용 JSP 파일명의  prefix, suffix 처리에 대한 mvc 설정  -->
    <bean class="org.springframework.web.servlet.view.UrlBasedViewResolver" p:order="1"
	    p:viewClass="org.springframework.web.servlet.view.JstlView"
	    p:prefix="/WEB-INF/jsp/" p:suffix=".jsp"/>
	
    <!-- DispatcherServlet이 찾지 못한 URL 들을 톰캣의 default-servlet 설정으로 넘겨준다 -->
    <mvc:default-servlet-handler/>
    
    <!-- 로그인 체크가 필요한 URL과 로그인 여부를 체크해준다 -->
    <mvc:interceptors>
        <mvc:interceptor>
            <mvc:mapping path="/cmm/main/*.do"/>
            <mvc:mapping path="/user/login/*.do"/>
            <mvc:mapping path="/admin/**"/>
            <mvc:mapping path="/ez*/**"/>
            <mvc:exclude-mapping path="/user/login/actionLogin.do"/>
            <mvc:exclude-mapping path="/user/login/getFidoSessionStatus.do"/>
            <mvc:exclude-mapping path="/user/login/expireFidoSession.do"/>
            <mvc:exclude-mapping path="/user/login/actionLogoutWithRedirectUri.do"/>            
            <mvc:exclude-mapping path="/user/login/login.do"/>
            <mvc:exclude-mapping path="/user/login/setTFA.do"/>
            <mvc:exclude-mapping path="/user/login/changePassword.do"/>
            <mvc:exclude-mapping path="/user/login/sendFindPwd.do"/>  
            <mvc:exclude-mapping path="/user/login/checkCertification.do"/>  
            <mvc:exclude-mapping path="/user/login/changePasswordByCertification.do"/>  
            <mvc:exclude-mapping path="/ezApprovalG/excelExportOut.do"/>
            <mvc:exclude-mapping path="/ezEmail/downloadAttachCommon.do"/>
            <mvc:exclude-mapping path="/ezEmail/downloadInlineDotNet.do"/>
            <mvc:exclude-mapping path="/ezEmail/readSecureMail.do"/>
            <mvc:exclude-mapping path="/ezEmail/readSecureMailContent.do"/>
            <mvc:exclude-mapping path="/ezEmail/downloadSecureAttach.do"/>
            <mvc:exclude-mapping path="/ezEmail/downloadSecureInline.do"/>
            <mvc:exclude-mapping path="/ezEmail/readExternalRecipient.do"/>
            <mvc:exclude-mapping path="/admin/ezApprovalG/componentListTransfer.do"/>
            <mvc:exclude-mapping path="/ezPortal/componentListTransfer.do"/>     
            <mvc:exclude-mapping path="/ezSystem/util/getSysInfo"/>   
            <mvc:exclude-mapping path="/ezSystem/util/getSysMonitorInfo" />
            <mvc:exclude-mapping path="/ezPortal/componentListTransfer.do"/>      
            <mvc:exclude-mapping path="/ezTalkGate/**"/>
            <mvc:exclude-mapping path="/ezConn/**"/>
            <mvc:exclude-mapping path="/ezUCMessenger/**"/>  
            <mvc:exclude-mapping path="/mobile/ezschedule/**"/>  
            <mvc:exclude-mapping path="/user/login/checkPasswordPolicy.do"/>  
            <mvc:exclude-mapping path="/ezSchedule/workspaceScheduleGetList.do"/>
            <mvc:exclude-mapping path="/ezApprovalG/downloadAttachForHwp.do"/>
		    <bean class="egovframework.com.cmm.interceptor.AuthenticInterceptor" />
        </mvc:interceptor>
        
        <mvc:interceptor>
            <mvc:mapping path="/admin/main.do"/>
            <!-- Top Menu -->
            <mvc:mapping path="/admin/top.do"/>
            <mvc:mapping path="/admin/ezPersonal/personalMain.do"/>
            <mvc:mapping path="/admin/ezOrgan/organMain.do"/>
            <mvc:mapping path="/admin/ezApproval/apprMain.do"/>
            <mvc:mapping path="/admin/ezApprovalG/apprGMain.do"/>
            <mvc:mapping path="/admin/ezBoard/boardMain.do"/>
            <mvc:mapping path="/admin/ezCommunity/communityMain.do"/>
            <mvc:mapping path="/admin/ezSchedule/scheduleMain.do"/>
            <mvc:mapping path="/ezStatistics/statisticsMain.do"/>
            <mvc:mapping path="/admin/ezNewPortal/portalMain.do"/>
            <mvc:mapping path="/admin/ezResource/resourceMain.do"/>
            <mvc:mapping path="/Myoffice/ezDocManagement/Admin/DocAdmin_index.html"/>
            <mvc:mapping path="/myoffice/ezKMS/admin/index_admin.aspx"/>
            <mvc:mapping path="/Myoffice/ezDMS/admin/index_admin.aspx"/>
            <mvc:mapping path="index_approval_Proc.htm"/>
            <mvc:mapping path="index_mobileMgmt.htm"/>
            <mvc:mapping path="/admin/ezSystem/systemMain.do"/>
            <mvc:mapping path="/admin/ezJournal/journalMain.do"/>
            <mvc:mapping path="/myoffice/ezStatistics/ezLog/index_Log.aspx"/>
            <mvc:mapping path="/admin/ezPMS/pmsMain.do"/>
            <mvc:mapping path="/admin/ezAttitude/attitudeMain.do"/>
            <mvc:mapping path="/admin/ezCabinet/cabinetAdminMain.do"/>
            <mvc:mapping path="/admin/ezEmail/adminMailMain.do"/>
            <mvc:mapping path="/admin/ezWebFolder/webFolderMain.do"/>
            <mvc:mapping path="/admin/ezCar/carMain.do"/>
            <!-- Left Menu -->
            	<!-- 포탈 -->
            	<mvc:mapping path="/admin/ezNewPortal/portalThemes.do"/>
            	<mvc:mapping path="/admin/ezNewPortal/portalMenus.do"/>
				<mvc:mapping path="/admin/ezNewPortal/portalPortlets.do"/>
				<mvc:mapping path="/admin/ezNewPortal/portalLogos.do"/>
				<mvc:mapping path="/admin/ezPersonal/manageNotice.do"/>
				<mvc:mapping path="/myoffice/ezPersonal/Link/ManageCompanyLink_Cross.aspx"/>
				<mvc:mapping path="/myoffice/ezPersonal/Link/ManageCompanyLink.aspx"/>
				<mvc:mapping path="/admin/ezPersonal/managePoll.do"/>
				<mvc:mapping path="/admin/ezPersonal/managePopup.do"/>
				<mvc:mapping path="/myoffice/ezPersonal/SuperPersonal/ManageSuperPersonal.aspx"/>
				<mvc:mapping path="/admin/ezPersonal/employeeOfMonth.do"/>
				<mvc:mapping path="/admin/ezPersonal/manageQuickLink.do"/>
				<mvc:mapping path="/admin/ezPersonal/sliderImages.do"/>
            	<!-- 조직도 -->
            	<mvc:mapping path="/admin/ezOrgan/organRight.do"/>
				<mvc:mapping path="/admin/ezOrgan/retireUserManage.do"/>
				<mvc:mapping path="/admin/ezOrgan/permissionsList.do"/>
				<mvc:mapping path="/admin/ezOrgan/addJobList.do"/>
				<mvc:mapping path="/admin/ezOrgan/jobInfoList.do"/>
				<mvc:mapping path="/admin/ezOrgan/loginStop.do"/>
				<mvc:mapping path="/admin/ezOrgan/groupList.do"/>
            	<!-- 메일 -->
				<mvc:mapping path="/admin/ezEmail/appr/*main.do"/>
            	<mvc:mapping path="/admin/ezEmail/mailDistributionList.do"/>
				<mvc:mapping path="/admin/ezEmail/mailDefaultQuota.do"/>
				<mvc:mapping path="/myoffice/ezEmail/Admin/mail_spamfilter_category.aspx"/>
				<mvc:mapping path="/myoffice/ezEmail/Admin/FormMaker.aspx"/>
				<mvc:mapping path="/myoffice/ezEmail/Admin/FormMaker_Cross.aspx"/>
				<mvc:mapping path="/myoffice/ezEmail/Admin/mail_approve_category.aspx"/>
				<mvc:mapping path="/myoffice/ezEmail/Admin/Right_DLSendManage.aspx"/>
				<mvc:mapping path="/myoffice/ezEmail/Admin/Right_DLSentItems.aspx"/>
				<mvc:mapping path="/admin/ezEmail/mailConfigColor.do"/>
				<mvc:mapping path="/myoffice/ezEmail/Admin/Right_LargeSizeMailManage.aspx"/>
				<mvc:mapping path="/admin/ezSystem/systemMainMenu.do"/>
				<mvc:mapping path="/myoffice/ezEmail/Admin/mail_DLMailConfig.aspx"/>
				<mvc:mapping path="/myoffice/ezEmail/DLmail_list.aspx"/>
				<mvc:mapping path="/admin/ezEmail/mailQuotaList.do"/>
				<mvc:mapping path="/ezStatistics/statisticsMailMain.do"/>
				<mvc:mapping path="/ezStatistics/statisticsMailDept.do"/>
				<mvc:mapping path="/ezStatistics/statisticsMailUser.do"/>
				<mvc:mapping path="/ezStatistics/statisticsQuantityDept.do"/>
				<mvc:mapping path="/ezStatistics/statisticsQuantityUser.do"/>
				<mvc:mapping path="/ezStatistics/statisticsMailRecieveLogList.do"/>
				<mvc:mapping path="/ezStatistics/statisticsMailSendLogList.do"/>
				<mvc:mapping path="/admin/ezEmail/letterMain.do"/>
				<mvc:mapping path="/admin/ezEmail/signatureMain.do"/>
				<mvc:mapping path="/admin/ezEmail/showSharedMailboxList.do"/>
				<mvc:mapping path="/admin/ezEmail/mailCopyright.do"/>
				<mvc:mapping path="/admin/ezEmail/multiDomain.do"/>
				<mvc:mapping path="/admin/ezEmail/companyMultiDomain.do"/>
            	<!-- 일정관리 -->
	            <mvc:mapping path="/admin/ezSchedule/scheduleAdminShareManage.do"/>
				<mvc:mapping path="/admin/ezSchedule/scheduleAdminShareManage.do"/>
				<mvc:mapping path="/admin/ezSchedule/scheduleAdminHolidayTab.do"/>
				<mvc:mapping path="/admin/ezSchedule/scheduleAdminLunarUse.do"/>
				<mvc:mapping path="/admin/ezSchedule/scheduleAdminRegi.do"/>
            	<!-- 게시판 -->
            	<mvc:mapping path="/admin/ezBoard/boardGroupCreate.do"/>
				<mvc:mapping path="/admin/ezBoard/boardCreate.do"/>
				<mvc:mapping path="/admin/ezBoard/boardOrder.do"/>
				<mvc:mapping path="/admin/ezBoard/boardMove.do"/>
				<mvc:mapping path="/admin/ezBoard/boardDelete.do"/>
				<mvc:mapping path="/admin/ezBoard/boardProperty.do"/>
				<mvc:mapping path="/admin/ezBoard/boardACL.do"/>
				<mvc:mapping path="/admin/ezBoard/boardBackGround.do"/>
            	<!-- 전자결재 -->
            	<mvc:mapping path="/admin/ezApprovalG/formAdmin.do"/>
				<mvc:mapping path="/admin/ezApprovalG/apprGMCont.do"/>
				<mvc:mapping path="/admin/ezApprovalG/apprGMoveContainer.do"/>
				<mvc:mapping path="/admin/ezApprovalG/docDelete.do"/>
				<mvc:mapping path="/admin/ezApprovalG/apprGReceiveGroup.do"/>
				<mvc:mapping path="/admin/ezApprovalG/apprGTaskCodeManage.do"/>
				<mvc:mapping path="/admin/ezApprovalG/taskAdminDept.do"/>
				<mvc:mapping path="/admin/ezApprovalG/manageSeal.do"/>
				<mvc:mapping path="/admin/ezApprovalG/manageDeptSeal.do"/>
				<mvc:mapping path="/admin/ezApprovalG/manageSendInfo.do"/>
				<mvc:mapping path="/admin/ezApprovalG/statistics.do"/>
				<mvc:mapping path="/admin/ezApprovalG/forAprDoc.do"/>
				<mvc:mapping path="/admin/ezApprovalG/forDoc.do"/>
				<mvc:mapping path="/admin/ezApprovalG/adminBujae.do"/>
				<mvc:mapping path="/admin/ezApprovalG/docNumZeroCnt.do"/>
				<mvc:mapping path="/admin/ezApprovalG/openGovForDoc.do"/>
				<mvc:mapping path="/admin/ezApprovalG/enforceSihangSeal.do"/>
            	<!-- 커뮤니티 -->
            	<mvc:mapping path="/admin/ezCommunity/searchKey.do"/>
				<mvc:mapping path="/admin/ezCommunity/bbsList.do"/>
				<mvc:mapping path="/admin/ezCommunity/applicationList.do"/>
            	<!-- 자원관리 -->
            	<mvc:mapping path="gwBoardListRegSubBoard.do"/>
				<mvc:mapping path="gwBoardListRegComBoard.do"/>
				<mvc:mapping path="gwBoardPostRegBoardRightMain.do"/>
				<mvc:mapping path="gwBoardPostRegBoardOrder.do"/>
				<mvc:mapping path="gwBoardPostBoardMove.do"/>
				<mvc:mapping path="gwBoardPostBoardDel.do"/>
				<mvc:mapping path="gwboardGetItemMoveSearch.do"/>
				<mvc:mapping path="gwboardGetItemMoveSearch.do"/>
				<mvc:mapping path="gwBoardPostRegGongjiBoard.do"/>
            	<!-- 시스템 -->
            	<mvc:mapping path="/admin/ezSystem/systemMainMenu.do"/>
				<mvc:mapping path="/admin/ezSystem/systemLoginHist.do"/>
				<mvc:mapping path="/admin/ezSystem/systemIPManager.do"/>
				<mvc:mapping path="/admin/ezSystem/sysREST.do"/>
				<mvc:mapping path="/admin/ezSystem/systemModuleMonitor.do"/>
				<mvc:mapping path="/admin/ezSystem/multiLoginManager.do"/>
				<mvc:mapping path="/admin/ezSystem/systemAdminIPManager.do"/>
				<mvc:mapping path="/admin/ezSystem/systemUserChangeHist.do"/>
            	<!-- 통계 -->
	            <mvc:mapping path="/ezStatistics/statisticsPerSonalMain.do"/>
				<mvc:mapping path="/ezStatistics/statisticsMailMain.do"/>
				<mvc:mapping path="/ezStatistics/statisticsApprMain.do"/>
				<mvc:mapping path="PageLog/PageLog_Main.aspx"/>
				<mvc:mapping path="WebLog_Statistics/WebLog_Main.asp"/>
				<mvc:mapping path="/ezStatistics/statisticsAttitudeMain.do"/>
            <!-- adminAccessBlockPage -->
            <mvc:exclude-mapping path="/admin/accessBlockToAdmin.do"/>
			<mvc:exclude-mapping path="/admin/adminDenied.do"/>
		    <bean class="egovframework.com.cmm.interceptor.AdminAccessInterceptor" />
        </mvc:interceptor>
        
        <mvc:interceptor>            
            <mvc:mapping path="/mobile/**"/>
            <mvc:mapping path="/rest/**"/>
            <mvc:exclude-mapping path="/rest/ezwebfolder/**"/>
            <mvc:exclude-mapping path="/rest/ezwebfolderadmin/**"/>
			<mvc:exclude-mapping path="/rest/MenuSchedule"/>
		    <bean class="egovframework.com.cmm.interceptor.MAuthenticInterceptor" />
        </mvc:interceptor>    

        <mvc:interceptor>            
            <mvc:mapping path="/rest/ezwebfolder/**"/>
            <mvc:mapping path="/rest/ezwebfolderadmin/**"/>
            <mvc:exclude-mapping path="/rest/ezwebfolder/login"/>
            <mvc:exclude-mapping path="/rest/ezwebfolder/file/sat" />
		    <bean class="egovframework.com.cmm.interceptor.WebfolderAuthenticInterceptor" />
        </mvc:interceptor>

		<mvc:interceptor>
			<mvc:mapping path="/admin/ezEmail/appr/allHands/*.do"/>
			<mvc:mapping path="/admin/ezEmail/appr/*.do"/>
			<mvc:mapping path="/ezEmail/appr/*.do"/>
			<mvc:exclude-mapping path="/ezEmail/appr/checkApprPolicy.do"/>
			<bean class="egovframework.com.cmm.interceptor.ApprMailAuthenticInterceptor" />
		</mvc:interceptor>

		<mvc:interceptor>
			<mvc:mapping path="/" />
			<mvc:mapping path="/ezNewPortal/**" />
			<mvc:mapping path="/user/login/email.do" />
			<!-- <mvc:exclude-mapping path="/rest/ezwebfolder/**" /> -->
			<bean class="egovframework.com.cmm.interceptor.UserEmailInterceptor" />
		</mvc:interceptor>
	</mvc:interceptors>

    <!-- Annotation 을 사용하지 않는 경우에 대한 MVC 처리 설정 -->
    <mvc:view-controller path="/cmmn/validator.do" view-name="cmmn/validator"/>
    
    <mvc:resources location="/css/" mapping="/css/**"/>
    <mvc:resources location="/js/" mapping="/js/**"/>
    <mvc:resources location="/images/" mapping="/images/**"/>
    <mvc:resources location="/images_en/" mapping="/images_en/**"/>
    <mvc:resources location="/images_ja/" mapping="/images_ja/**"/>
    <mvc:resources location="/files/" mapping="/files/**"/>
    <mvc:resources location="/docs/" mapping="/docs/**"/>
    
	<bean id="contentNegotiationManager" class="org.springframework.web.accept.ContentNegotiationManagerFactoryBean">
		<property name="favorPathExtension" value="false" />
	</bean>
    
    <mvc:annotation-driven content-negotiation-manager="contentNegotiationManager" />

	<websocket:message-broker application-destination-prefix="/app" user-destination-prefix="/user">		
	    <websocket:stomp-endpoint path="/hello" >  	    	 	
			<websocket:sockjs />
	    </websocket:stomp-endpoint>
	    <websocket:simple-broker prefix="/reply, /topic, /message, /lad"/>
	</websocket:message-broker>
		
</beans>
